README.md
setup.cfg
setup.py
ccindividual/__init__.py
ccindividual/ex_loader.py
ccindividual/fail_exception.py
ccindividual.egg-info/PKG-INFO
ccindividual.egg-info/SOURCES.txt
ccindividual.egg-info/dependency_links.txt
ccindividual.egg-info/entry_points.txt
ccindividual.egg-info/requires.txt
ccindividual.egg-info/top_level.txt
ccindividual/exchanges/__init__.py
ccindividual/exchanges/okex/__init__.py
ccindividual/exchanges/okex/code_converter.py
ccindividual/exchanges/okex/trade_rest.py
ccindividual/exchanges/okex/sdk/__init__.py
ccindividual/exchanges/okex/sdk/account_api.py
ccindividual/exchanges/okex/sdk/client.py
ccindividual/exchanges/okex/sdk/consts.py
ccindividual/exchanges/okex/sdk/ett_api.py
ccindividual/exchanges/okex/sdk/exceptions.py
ccindividual/exchanges/okex/sdk/futures_api.py
ccindividual/exchanges/okex/sdk/lever_api.py
ccindividual/exchanges/okex/sdk/spot_api.py
ccindividual/exchanges/okex/sdk/swap_api.py
ccindividual/exchanges/okex/sdk/utils.py
ccindividual/exchanges/okex/sdk/websocket.py