Metadata-Version: 2.1
Name: ccindividual
Version: 0.1.0
Summary: Crypto Currency Individual
Home-page: https://gitlab.com/dozenc/ccindividual
Author: dozenc
Author-email: dozenc@outlook.com
License: UNKNOWN
Project-URL: Bug Reports, https://gitlab.com/dozenc/ccindividual
Project-URL: Funding, https://gitlab.com/dozenc/ccindividual
Project-URL: Say Thanks!, https://gitlab.com/dozenc/ccindividual
Project-URL: Source, https://gitlab.com/dozenc/ccindividual
Keywords: Crypto Currency Exchange
Platform: UNKNOWN
Classifier: Development Status :: 3 - Alpha
Classifier: Intended Audience :: Developers
Classifier: Topic :: Software Development :: Build Tools
Classifier: License :: OSI Approved :: MIT License
Classifier: Programming Language :: Python :: 3.5
Classifier: Programming Language :: Python :: 3.6
Classifier: Programming Language :: Python :: 3.7
Requires-Python: >=3.5, <4
Provides-Extra: test
Provides-Extra: dev
